[
  {
    "artista": "Iván_(cantante)",
    "fecha": "2019-03-18",
    "visitas": 95
  },
  {
    "artista": "Iván_(cantante)",
    "fecha": "2019-03-19",
    "visitas": 122
  },
  {
    "artista": "Iván_(cantante)",
    "fecha": "2019-03-20",
    "visitas": 75
  },
  {
    "artista": "Iván_(cantante)",
    "fecha": "2019-03-21",
    "visitas": 78
  },
  {
    "artista": "Iván_(cantante)",
    "fecha": "2019-03-22",
    "visitas": 74
  },
  {
    "artista": "Iván_(cantante)",
    "fecha": "2019-03-23",
    "visitas": 76
  },
  {
    "artista": "Iván_(cantante)",
    "fecha": "2019-03-24",
    "visitas": 95
  },
  {
    "artista": "Iván_(cantante)",
    "fecha": "2019-03-25",
    "visitas": 90
  },
  {
    "artista": "Iván_(cantante)",
    "fecha": "2019-03-26",
    "visitas": 81
  },
  {
    "artista": "Iván_(cantante)",
    "fecha": "2019-03-27",
    "visitas": 67
  },
  {
    "artista": "Iván_(cantante)",
    "fecha": "2019-03-28",
    "visitas": 73
  },
  {
    "artista": "Iván_(cantante)",
    "fecha": "2019-03-29",
    "visitas": 86
  },
  {
    "artista": "Iván_(cantante)",
    "fecha": "2019-03-30",
    "visitas": 90
  },
  {
    "artista": "Iván_(cantante)",
    "fecha": "2019-03-31",
    "visitas": 93
  },
  {
    "artista": "Iván_(cantante)",
    "fecha": "2019-04-01",
    "visitas": 73
  },
  {
    "artista": "Iván_(cantante)",
    "fecha": "2019-04-02",
    "visitas": 63
  },
  {
    "artista": "Iván_(cantante)",
    "fecha": "2019-04-03",
    "visitas": 68
  },
  {
    "artista": "Iván_(cantante)",
    "fecha": "2019-04-04",
    "visitas": 78
  },
  {
    "artista": "Iván_(cantante)",
    "fecha": "2019-04-05",
    "visitas": 69
  },
  {
    "artista": "Iván_(cantante)",
    "fecha": "2019-04-06",
    "visitas": 85
  },
  {
    "artista": "Iván_(cantante)",
    "fecha": "2019-04-07",
    "visitas": 105
  },
  {
    "artista": "Iván_(cantante)",
    "fecha": "2019-04-08",
    "visitas": 71
  },
  {
    "artista": "Iván_(cantante)",
    "fecha": "2019-04-09",
    "visitas": 81
  },
  {
    "artista": "Iván_(cantante)",
    "fecha": "2019-04-10",
    "visitas": 74
  },
  {
    "artista": "Iván_(cantante)",
    "fecha": "2019-04-11",
    "visitas": 79
  },
  {
    "artista": "Iván_(cantante)",
    "fecha": "2019-04-12",
    "visitas": 69
  },
  {
    "artista": "Iván_(cantante)",
    "fecha": "2019-04-13",
    "visitas": 71
  },
  {
    "artista": "Iván_(cantante)",
    "fecha": "2019-04-14",
    "visitas": 72
  },
  {
    "artista": "Iván_(cantante)",
    "fecha": "2019-04-15",
    "visitas": 80
  },
  {
    "artista": "Iván_(cantante)",
    "fecha": "2019-04-16",
    "visitas": 71
  },
  {
    "artista": "Iván_(cantante)",
    "fecha": "2019-04-17",
    "visitas": 76
  },
  {
    "artista": "Iván_(cantante)",
    "fecha": "2019-04-18",
    "visitas": 74
  },
  {
    "artista": "Iván_(cantante)",
    "fecha": "2019-04-19",
    "visitas": 88
  },
  {
    "artista": "Iván_(cantante)",
    "fecha": "2019-04-20",
    "visitas": 84
  },
  {
    "artista": "Iván_(cantante)",
    "fecha": "2019-04-21",
    "visitas": 75
  },
  {
    "artista": "Iván_(cantante)",
    "fecha": "2019-04-22",
    "visitas": 76
  },
  {
    "artista": "Iván_(cantante)",
    "fecha": "2019-04-23",
    "visitas": 691
  },
  {
    "artista": "Iván_(cantante)",
    "fecha": "2019-04-24",
    "visitas": 91
  },
  {
    "artista": "Iván_(cantante)",
    "fecha": "2019-04-25",
    "visitas": 83
  },
  {
    "artista": "Iván_(cantante)",
    "fecha": "2019-04-26",
    "visitas": 86
  },
  {
    "artista": "Iván_(cantante)",
    "fecha": "2019-04-27",
    "visitas": 70
  },
  {
    "artista": "Iván_(cantante)",
    "fecha": "2019-04-28",
    "visitas": 73
  },
  {
    "artista": "Iván_(cantante)",
    "fecha": "2019-04-29",
    "visitas": 58
  },
  {
    "artista": "Iván_(cantante)",
    "fecha": "2019-04-30",
    "visitas": 86
  },
  {
    "artista": "Iván_(cantante)",
    "fecha": "2019-05-01",
    "visitas": 81
  },
  {
    "artista": "Iván_(cantante)",
    "fecha": "2019-05-02",
    "visitas": 76
  },
  {
    "artista": "Iván_(cantante)",
    "fecha": "2019-05-03",
    "visitas": 127
  },
  {
    "artista": "Iván_(cantante)",
    "fecha": "2019-05-04",
    "visitas": 70
  },
  {
    "artista": "Iván_(cantante)",
    "fecha": "2019-05-05",
    "visitas": 73
  },
  {
    "artista": "Iván_(cantante)",
    "fecha": "2019-05-06",
    "visitas": 64
  },
  {
    "artista": "Iván_(cantante)",
    "fecha": "2019-05-07",
    "visitas": 74
  },
  {
    "artista": "Iván_(cantante)",
    "fecha": "2019-05-08",
    "visitas": 67
  },
  {
    "artista": "Iván_(cantante)",
    "fecha": "2019-05-09",
    "visitas": 54
  },
  {
    "artista": "Iván_(cantante)",
    "fecha": "2019-05-10",
    "visitas": 82
  },
  {
    "artista": "Iván_(cantante)",
    "fecha": "2019-05-11",
    "visitas": 90
  },
  {
    "artista": "Iván_(cantante)",
    "fecha": "2019-05-12",
    "visitas": 102
  },
  {
    "artista": "Iván_(cantante)",
    "fecha": "2019-05-13",
    "visitas": 66
  },
  {
    "artista": "Iván_(cantante)",
    "fecha": "2019-05-14",
    "visitas": 86
  },
  {
    "artista": "Iván_(cantante)",
    "fecha": "2019-05-15",
    "visitas": 143
  },
  {
    "artista": "Iván_(cantante)",
    "fecha": "2019-05-16",
    "visitas": 114
  },
  {
    "artista": "Iván_(cantante)",
    "fecha": "2019-05-17",
    "visitas": 113
  },
  {
    "artista": "Iván_(cantante)",
    "fecha": "2019-05-18",
    "visitas": 101
  },
  {
    "artista": "Iván_(cantante)",
    "fecha": "2019-05-19",
    "visitas": 126
  },
  {
    "artista": "Iván_(cantante)",
    "fecha": "2019-05-20",
    "visitas": 107
  },
  {
    "artista": "Iván_(cantante)",
    "fecha": "2019-05-21",
    "visitas": 87
  },
  {
    "artista": "Iván_(cantante)",
    "fecha": "2019-05-22",
    "visitas": 95
  },
  {
    "artista": "Iván_(cantante)",
    "fecha": "2019-05-23",
    "visitas": 94
  },
  {
    "artista": "Iván_(cantante)",
    "fecha": "2019-05-24",
    "visitas": 97
  },
  {
    "artista": "Iván_(cantante)",
    "fecha": "2019-05-25",
    "visitas": 118
  },
  {
    "artista": "Iván_(cantante)",
    "fecha": "2019052600",
    "visitas": 93
  },
  {
    "artista": "Iván_(cantante)",
    "fecha": "2019052700",
    "visitas": 122
  },
  {
    "artista": "Iván_(cantante)",
    "fecha": "2019052800",
    "visitas": 79
  },
  {
    "artista": "Iván_(cantante)",
    "fecha": "2019052900",
    "visitas": 84
  },
  {
    "artista": "Iván_(cantante)",
    "fecha": "2019053000",
    "visitas": 68
  },
  {
    "artista": "Iván_(cantante)",
    "fecha": "2019053100",
    "visitas": 72
  },
  {
    "artista": "Iván_(cantante)",
    "fecha": "2019060100",
    "visitas": 106
  },
  {
    "artista": "Iván_(cantante)",
    "fecha": "2019060200",
    "visitas": 102
  },
  {
    "artista": "Iván_(cantante)",
    "fecha": "2019060300",
    "visitas": 75
  },
  {
    "artista": "Iván_(cantante)",
    "fecha": "2019060400",
    "visitas": 97
  },
  {
    "artista": "Iván_(cantante)",
    "fecha": "2019060500",
    "visitas": 72
  },
  {
    "artista": "Iván_(cantante)",
    "fecha": "2019060600",
    "visitas": 69
  },
  {
    "artista": "Iván_(cantante)",
    "fecha": "2019060700",
    "visitas": 88
  },
  {
    "artista": "Iván_(cantante)",
    "fecha": "2019060800",
    "visitas": 88
  },
  {
    "artista": "Iván_(cantante)",
    "fecha": "2019060900",
    "visitas": 85
  },
  {
    "artista": "Iván_(cantante)",
    "fecha": "2019061000",
    "visitas": 62
  },
  {
    "artista": "Iván_(cantante)",
    "fecha": "2019061100",
    "visitas": 81
  },
  {
    "artista": "Iván_(cantante)",
    "fecha": "2019061200",
    "visitas": 98
  },
  {
    "artista": "Iván_(cantante)",
    "fecha": "2019061300",
    "visitas": 75
  },
  {
    "artista": "Iván_(cantante)",
    "fecha": "2019061400",
    "visitas": 110
  },
  {
    "artista": "Iván_(cantante)",
    "fecha": "2019061500",
    "visitas": 85
  },
  {
    "artista": "Iván_(cantante)",
    "fecha": "2019061600",
    "visitas": 100
  },
  {
    "artista": "Iván_(cantante)",
    "fecha": "2019061700",
    "visitas": 92
  },
  {
    "artista": "Iván_(cantante)",
    "fecha": "2019061800",
    "visitas": 548
  },
  {
    "artista": "Iván_(cantante)",
    "fecha": "2019061900",
    "visitas": 112
  }
]
