[
  {
    "artista": "Alaska_y_Dinarama",
    "fecha": "2019032400",
    "visitas": 0
  },
  {
    "artista": "Alaska_y_Dinarama",
    "fecha": "2019032500",
    "visitas": 2
  },
  {
    "artista": "Alaska_y_Dinarama",
    "fecha": "2019032600",
    "visitas": 1
  },
  {
    "artista": "Alaska_y_Dinarama",
    "fecha": "2019032700",
    "visitas": 0
  },
  {
    "artista": "Alaska_y_Dinarama",
    "fecha": "2019032800",
    "visitas": 1
  },
  {
    "artista": "Alaska_y_Dinarama",
    "fecha": "2019032900",
    "visitas": 1
  },
  {
    "artista": "Alaska_y_Dinarama",
    "fecha": "2019033000",
    "visitas": 1
  },
  {
    "artista": "Alaska_y_Dinarama",
    "fecha": "2019033100",
    "visitas": 1
  },
  {
    "artista": "Alaska_y_Dinarama",
    "fecha": "2019040100",
    "visitas": 0
  },
  {
    "artista": "Alaska_y_Dinarama",
    "fecha": "2019040200",
    "visitas": 3
  },
  {
    "artista": "Alaska_y_Dinarama",
    "fecha": "2019040300",
    "visitas": 2
  },
  {
    "artista": "Alaska_y_Dinarama",
    "fecha": "2019040400",
    "visitas": 1
  },
  {
    "artista": "Alaska_y_Dinarama",
    "fecha": "2019040500",
    "visitas": 1
  },
  {
    "artista": "Alaska_y_Dinarama",
    "fecha": "2019040600",
    "visitas": 3
  },
  {
    "artista": "Alaska_y_Dinarama",
    "fecha": "2019040700",
    "visitas": 14
  },
  {
    "artista": "Alaska_y_Dinarama",
    "fecha": "2019040800",
    "visitas": 1
  },
  {
    "artista": "Alaska_y_Dinarama",
    "fecha": "2019040900",
    "visitas": 2
  },
  {
    "artista": "Alaska_y_Dinarama",
    "fecha": "2019041000",
    "visitas": 2
  },
  {
    "artista": "Alaska_y_Dinarama",
    "fecha": "2019041100",
    "visitas": 1
  },
  {
    "artista": "Alaska_y_Dinarama",
    "fecha": "2019041200",
    "visitas": 2
  },
  {
    "artista": "Alaska_y_Dinarama",
    "fecha": "2019041300",
    "visitas": 1
  },
  {
    "artista": "Alaska_y_Dinarama",
    "fecha": "2019041400",
    "visitas": 2
  },
  {
    "artista": "Alaska_y_Dinarama",
    "fecha": "2019041500",
    "visitas": 1
  },
  {
    "artista": "Alaska_y_Dinarama",
    "fecha": "2019041600",
    "visitas": 5
  },
  {
    "artista": "Alaska_y_Dinarama",
    "fecha": "2019041700",
    "visitas": 1
  },
  {
    "artista": "Alaska_y_Dinarama",
    "fecha": "2019041800",
    "visitas": 1
  },
  {
    "artista": "Alaska_y_Dinarama",
    "fecha": "2019041900",
    "visitas": 1
  },
  {
    "artista": "Alaska_y_Dinarama",
    "fecha": "2019042000",
    "visitas": 1
  },
  {
    "artista": "Alaska_y_Dinarama",
    "fecha": "2019042100",
    "visitas": 7
  },
  {
    "artista": "Alaska_y_Dinarama",
    "fecha": "2019042200",
    "visitas": 0
  },
  {
    "artista": "Alaska_y_Dinarama",
    "fecha": "2019042300",
    "visitas": 0
  },
  {
    "artista": "Alaska_y_Dinarama",
    "fecha": "2019042400",
    "visitas": 5
  }
]
